LICENSE
MANIFEST.in
README.rst
setup.cfg
setup.py
httpobs_cli.egg-info/PKG-INFO
httpobs_cli.egg-info/SOURCES.txt
httpobs_cli.egg-info/dependency_links.txt
httpobs_cli.egg-info/entry_points.txt
httpobs_cli.egg-info/requires.txt
httpobs_cli.egg-info/top_level.txt
httpobs_cli.egg-info/zip-safe
httpobscli/__init__.py
httpobscli/cli.py