Metadata-Version: 1.1
Name: httpobs-cli
Version: 1.0.2
Summary: HTTP Observatory: a command line tool to scan your website
Home-page: https://github.com/mozilla/http-observatory-cli
Author: April King
Author-email: april@mozilla.com
License: MPL 2.0
Download-URL: https://github.com/mozilla/http-observatory-cli/httpobs-cli/tarball/1.0.2
Platform: UNKNOWN
Classifier: Development Status :: 4 - Beta
Classifier: Environment :: Web Environment
Classifier: Intended Audience :: Developers
Classifier: Intended Audience :: System Administrators
Classifier: License :: OSI Approved :: Mozilla Public License 2.0 (MPL 2.0)
Classifier: Natural Language :: English
Classifier: Topic :: Security
Classifier: Topic :: Software Development :: Quality Assurance
Classifier: Topic :: Internet :: WWW/HTTP :: HTTP Servers
